toker/__init__.py
toker-0.1.0.dist-info/WHEEL
toker-0.1.0.dist-info/entry_points.txt
toker-0.1.0.dist-info/METADATA
toker-0.1.0.dist-info/RECORD
